dev/sram/sram.v
`default_nettype none
module sram( 
    	input reset,
	input clk,				// external clock 100 MHz	
	input [9:0] block,
	output reg [17:0] sram_addr,		// SRAM Address 18 Bit = 256K
	inout [15:0] sram_data,			// SRAM Data 16 Bit
	output reg sram_wen,			// SRAM write_enable_not
	output reg sram_oen,			// SRAM output_enable_not
	output reg sram_cen, 			// SRAM chip_enable_not
	input wire startW,
	input wire startR,
	input wire [11:0] mix_addr_in,
	output reg [11:0] mix_addr_out,
	input wire [30:0] mix_data_in,
	output reg [30:0] mix_data_out,
	output reg mix_read,
	output reg mix_write
);
	reg start2;
	always @(posedge clk)
		if (startW) start2 <=1;
		else start2 <= 0;
	reg startR2;
	always @(posedge clk)
		if (startR) startR2 <=1;
		else startR2 <= 0;


	always @(posedge clk)
		if (startW|startR) sram_addr <= {block,7'd0};
		else if (~start2& ~startR2 & count[0]) sram_addr <= sram_addr + 1;

	always @(posedge clk)
		if (startW|startR) mix_addr_out <= mix_addr_in;
		else if (write &  count ==2'd2) mix_addr_out <= mix_addr_out + 1;
		else if (read &  count ==2'd3) mix_addr_out <= mix_addr_out + 1;

	always @(posedge clk)
		if (startW | (write & (count ==2'd2))) mix_read <= 1;
		else mix_read <= 0;
	always @(posedge clk)
		if ((read & (count ==2'd2))) mix_write <= 1;
		else mix_write <= 0;
	
	assign dataW = (count ==2'd0)? mix_data_in[15:0] : datan;

	reg [15:0] datah;
	always @(posedge clk)
		if (count==2'd0) datah <= {1'd0,mix_data_in[30:16]};
	reg [15:0] datan;
	always @(posedge clk)
		if (count==2'd0) datan <= dataW;
		else if (count==2'd1) datan <= datah;
	
	wire last;
	assign last = (sram_addr[6:0] == 7'd11) & (count == 2'd3);

	always @(posedge clk)
		if (read & (count==2'd0)) mix_data_out <= {15'd0,sram_data};
		else if (read & (count==2'd2)) mix_data_out <= {sram_data[14:0],mix_data_out[15:0]};


	reg [1:0] count;
	always @(posedge clk)
		if (startW|startR) count <= 2'd0;
		else if (write|read) count <= count + 1;


	always @(posedge clk)
		if (reset) sram_wen <= 1;
		else if (write & ~count[0]) sram_wen <= 0;
		else sram_wen <= 1;
	always @(posedge clk)
		if (reset) sram_oen <= 1;
		else if (startR2) sram_oen <= 0;
		else if (last) sram_oen <= 1;
	always @(posedge clk)
		if (reset) sram_cen <= 1;
		else if (start2|startR2) sram_cen <= 0;
		else if (last) sram_cen <= 1;
	reg read;
	always @(posedge clk)
		if (reset) read <= 0;
		else if (startR2) read <= 1;
		else if (last) read <= 0;

	reg write;
	always @(posedge clk)
		if (reset) write <= 0;
		else if (start2) write <= 1;
		else if (last) write <= 0;
	wire [15:0] dataW;
	assign sram_data = (write)? dataW: 16'bzzzzzzzzzzzzzzzz;
	
endmodule

dev/sram/sram_tb.v
`default_nettype none
`define DUMPSTR(x) `"x.vcd`"
`timescale 100 ns / 10 ns

module sram_tb();

//-- Simulation time: 1us (10 * 100ns)
parameter DURATION = 100000;

//-- Clock signal. It is not used in this simulation
reg clk = 0;
always #0.5 clk = ~clk;
reg reset = 1;
reg startW=0;
reg startR=0;
wire [11:0] mix_addr_out;
reg [30:0] mix_data;
wire mix_read;
reg [31:0] data[100];
always @(posedge clk)
	if (mix_read) mix_data <= data[mix_addr_out];
	else mix_data <=0;

initial begin
	data[0] = 32'd5555555555;
	data[1] = 32'd5555555555;
	data[2] = 32'd5555555555;
	data[3] = 32'd5555555555;
	data[4] = 32'd5555555555;
	data[5] = 32'd55555;
	data[6] = 32'd55555;
	data[7] = 32'd55555;
	data[8] = 32'd55555;
	data[9] = 32'd55555;
	data[10] = 32'd66666;

end

//-- Instantiate the unit to test
sram SRAM(
	   .clk(clk),
	   .reset(reset),
	   .startW(startW),
	   .startR(startR),
	   .block(10'd555),
	   .mix_read(mix_read),
	   .mix_addr_out(mix_addr_out),
	   .mix_data_in(mix_data),
	   .mix_addr_in(12'd0)
         );


initial begin

  //-- File were to store the simulation results
  $dumpfile(`DUMPSTR(`VCD_OUTPUT));
  $dumpvars(0, sram_tb);
  	#3 reset <= 0;
	#1 startW <= 1;
	#1 startW <= 0;
	#50 startR <= 1;
	#1 startR <= 0;
   #(DURATION) $display("End of simulation");
  $finish;
end

endmodule

dev/sram/sram_tb.vcd
$date
	Sun May 16 16:53:58 2021
$end
$version
	Icarus Verilog
$end
$timescale
	1ps
$end
$scope module sram_tb $end
$var wire 1 ! mix_read $end
$var wire 12 " mix_addr_out [11:0] $end
$var reg 1 # clk $end
$var reg 31 $ mix_data [30:0] $end
$var reg 1 % reset $end
$var reg 1 & startR $end
$var reg 1 ' startW $end
$scope module SRAM $end
$var wire 10 ( block [9:0] $end
$var wire 1 # clk $end
$var wire 1 ) last $end
$var wire 12 * mix_addr_in [11:0] $end
$var wire 31 + mix_data_in [30:0] $end
$var wire 1 % reset $end
$var wire 1 & startR $end
$var wire 1 ' startW $end
$var wire 16 , sram_data [15:0] $end
$var wire 16 - dataW [15:0] $end
$var reg 2 . count [1:0] $end
$var reg 16 / datah [15:0] $end
$var reg 16 0 datan [15:0] $end
$var reg 12 1 mix_addr_out [11:0] $end
$var reg 31 2 mix_data_out [30:0] $end
$var reg 1 ! mix_read $end
$var reg 1 3 mix_write $end
$var reg 1 4 read $end
$var reg 18 5 sram_addr [17:0] $end
$var reg 1 6 sram_cen $end
$var reg 1 7 sram_oen $end
$var reg 1 8 sram_wen $end
$var reg 1 9 start2 $end
$var reg 1 : startR2 $end
$var reg 1 ; write $end
$upscope $end
$upscope $end
$enddefinitions $end
#0
$dumpvars
x;
x:
x9
x8
x7
x6
bx 5
x4
x3
bx 2
bx 1
bx 0
bx /
bx .
bx -
bx ,
bx +
b0 *
x)
b1000101011 (
0'
0&
1%
bx $
0#
bx "
x!
$end
#50000
bz ,
09
0:
0!
03
18
17
16
04
0;
b0 $
b0 +
1#
#100000
0#
#150000
1#
#200000
0#
#250000
1#
#300000
0%
0#
#350000
1#
#400000
1'
0#
#450000
b0 -
0)
19
b10001010110000000 5
b0 "
b0 1
1!
b0 .
1#
#500000
0'
0#
#550000
b110011100011 -
b110011100011 ,
b1001011001000110000110011100011 $
b1001011001000110000110011100011 +
1;
06
b0 0
b0 /
0!
09
1#
#600000
0#
#650000
b100101100100011 /
b110011100011 0
b1 .
08
b0 $
b0 +
1#
#700000
0#
#750000
b100101100100011 ,
b100101100100011 -
18
b10 .
b100101100100011 0
b10001010110000001 5
1#
#800000
0#
#850000
b1 "
b1 1
1!
b11 .
08
1#
#900000
0#
#950000
b110011100011 ,
b110011100011 -
b1001011001000110000110011100011 $
b1001011001000110000110011100011 +
18
b0 .
0!
b10001010110000010 5
1#
#1000000
0#
#1050000
b110011100011 0
b1 .
08
b0 $
b0 +
1#
#1100000
0#
#1150000
b100101100100011 ,
b100101100100011 -
18
b10 .
b100101100100011 0
b10001010110000011 5
1#
#1200000
0#
#1250000
b10 "
b10 1
1!
b11 .
08
1#
#1300000
0#
#1350000
b110011100011 ,
b110011100011 -
b1001011001000110000110011100011 $
b1001011001000110000110011100011 +
18
b0 .
0!
b10001010110000100 5
1#
#1400000
0#
#1450000
b110011100011 0
b1 .
08
b0 $
b0 +
1#
#1500000
0#
#1550000
b100101100100011 ,
b100101100100011 -
18
b10 .
b100101100100011 0
b10001010110000101 5
1#
#1600000
0#
#1650000
b11 "
b11 1
1!
b11 .
08
1#
#1700000
0#
#1750000
b110011100011 ,
b110011100011 -
b1001011001000110000110011100011 $
b1001011001000110000110011100011 +
18
b0 .
0!
b10001010110000110 5
1#
#1800000
0#
#1850000
b110011100011 0
b1 .
08
b0 $
b0 +
1#
#1900000
0#
#1950000
b100101100100011 ,
b100101100100011 -
18
b10 .
b100101100100011 0
b10001010110000111 5
1#
#2000000
0#
#2050000
b100 "
b100 1
1!
b11 .
08
1#
#2100000
0#
#2150000
b110011100011 ,
b110011100011 -
b1001011001000110000110011100011 $
b1001011001000110000110011100011 +
18
b0 .
0!
b10001010110001000 5
1#
#2200000
0#
#2250000
b110011100011 0
b1 .
08
b0 $
b0 +
1#
#2300000
0#
#2350000
b100101100100011 ,
b100101100100011 -
18
b10 .
b100101100100011 0
b10001010110001001 5
1#
#2400000
0#
#2450000
b101 "
b101 1
1!
b11 .
08
1#
#2500000
0#
#2550000
b1101100100000011 ,
b1101100100000011 -
b1101100100000011 $
b1101100100000011 +
18
b0 .
0!
b10001010110001010 5
1#
#2600000
0#
#2650000
b0 /
b1101100100000011 0
b1 .
08
b0 $
b0 +
1#
#2700000
0#
#2750000
b0 ,
b0 -
18
b10 .
b0 0
b10001010110001011 5
1#
#2800000
0#
#2850000
1)
b110 "
b110 1
1!
b11 .
08
1#
#2900000
0#
#2950000
b1101100100000011 -
bz ,
0)
b1101100100000011 $
b1101100100000011 +
0;
16
18
b0 .
0!
b10001010110001100 5
1#
#3000000
0#
#3050000
b0 -
b1101100100000011 0
b0 $
b0 +
1#
#3100000
0#
#3150000
b0 0
1#
