dev/rtltb/sram.v
`default_nettype none
module sram( 
    	input reset,
	input clk,				// external clock 100 MHz	
	input [9:0] block,
	output reg [17:0] sram_addr,		// SRAM Address 18 Bit = 256K
	inout [15:0] sram_data,			// SRAM Data 16 Bit
	output wire sram_wen,			// SRAM write_enable_not
	output wire sram_oen,			// SRAM output_enable_not
	output wire sram_cen, 			// SRAM chip_enable_not
	input wire startW,
	input wire startR,
	input wire [11:0] mix_addr_in,
	output reg [11:0] mix_addr_out,
	input wire [30:0] mix_data_in,
	output reg [30:0] mix_data_out,
	output reg mix_read,
	output reg mix_write,
	output wire stop
);
	assign stop = last;
	reg start2;
	always @(posedge clk)
		if (startW) start2 <=1;
		else start2 <= 0;
	reg startR2;
	always @(posedge clk)
		if (startR) startR2 <=1;
		else startR2 <= 0;


	always @(posedge clk)
		if (startW|startR) sram_addr <= {block,8'd0};
		else if (~start2& ~startR2 & count[0]) sram_addr <= sram_addr + 1;

	always @(posedge clk)
		if (startW|startR) mix_addr_out <= mix_addr_in;
		else if (write &  count ==2'd2) mix_addr_out <= mix_addr_out + 1;
		else if (read &  count ==2'd3) mix_addr_out <= mix_addr_out + 1;

	always @(posedge clk)
		if (startW | (write & (count ==2'd2))) mix_read <= 1;
		else mix_read <= 0;
	always @(posedge clk)
		if ((read & (count ==2'd2))) mix_write <= 1;
		else mix_write <= 0;
	
	assign dataW = (count ==2'd0)? mix_data_in[15:0] : datan;

	reg [15:0] datah;
	always @(posedge clk)
		if (count==2'd0) datah <= {1'd0,mix_data_in[30:16]};
	reg [15:0] datan;
	always @(posedge clk)
		if (count==2'd0) datan <= dataW;
		else if (count==2'd1) datan <= datah;
	
	wire last;
	assign last = (sram_addr[7:0] == 8'd199) & (count == 2'd3);

	always @(posedge clk)
		if (read & (count==2'd0)) mix_data_out <= {15'd0,sram_data};
		else if (read & (count==2'd2)) mix_data_out <= {sram_data[14:0],mix_data_out[15:0]};


	reg [1:0] count=0;
	always @(posedge clk)
		if (startW|startR) count <= 2'd0;
		else if (write|read) count <= count + 1;

	reg sram_we;
	assign sram_wen = ~ sram_we;
	always @(posedge clk)
		if (reset) sram_we <= 0;
		else if (write & ~count[0]) sram_we <= 1;
		else sram_we <= 0;
	reg sram_oe;
	assign sram_oen = ~sram_oe;
	always @(posedge clk)
		if (reset) sram_oe <= 0;
		else if (startR2) sram_oe <= 1;
		else if (last) sram_oe <= 0;
	reg sram_ce;
	assign sram_cen=~sram_ce;
	always @(posedge clk)
		if (reset) sram_ce <= 0;
		else if (start2|startR2) sram_ce <= 1;
		else if (last) sram_ce <= 0;
	reg read;
	always @(posedge clk)
		if (reset) read <= 0;
		else if (startR2) read <= 1;
		else if (last) read <= 0;

	reg write;
	always @(posedge clk)
		if (reset) write <= 0;
		else if (start2) write <= 1;
		else if (last) write <= 0;
	wire [15:0] dataW;
	assign sram_data = (write)? dataW: 16'bzzzzzzzzzzzzzzzz;
	
endmodule

dev/sram/sram_tb.v
`default_nettype none
`define DUMPSTR(x) `"x.vcd`"
`timescale 100 ns / 10 ns

module sram_tb();

//-- Simulation time: 1us (10 * 100ns)
parameter DURATION = 100000;

//-- Clock signal. It is not used in this simulation
reg clk = 0;
always #0.5 clk = ~clk;
reg reset = 1;
reg startW=0;
reg startR=0;
wire [11:0] mix_addr_out;
reg [30:0] mix_data;
wire mix_read;
reg [31:0] data[100];
always @(posedge clk)
	if (mix_read) mix_data <= data[mix_addr_out];
	else mix_data <=0;

initial begin
	data[0] = 32'd5555555555;
	data[1] = 32'd5555555555;
	data[2] = 32'd5555555555;
	data[3] = 32'd5555555555;
	data[4] = 32'd5555555555;
	data[5] = 32'd55555;
	data[6] = 32'd55555;
	data[7] = 32'd55555;
	data[8] = 32'd55555;
	data[9] = 32'd55555;
	data[10] = 32'd66666;

end

//-- Instantiate the unit to test
sram SRAM(
	   .clk(clk),
	   .reset(reset),
	   .startW(startW),
	   .startR(startR),
	   .block(10'd555),
	   .mix_read(mix_read),
	   .mix_addr_out(mix_addr_out),
	   .mix_data_in(mix_data),
	   .mix_addr_in(12'd0)
         );


initial begin

  //-- File were to store the simulation results
  $dumpfile(`DUMPSTR(`VCD_OUTPUT));
  $dumpvars(0, sram_tb);
  	#3 reset <= 0;
	#1 startW <= 1;
	#1 startW <= 0;
	#50 startR <= 1;
	#1 startR <= 0;
   #(DURATION) $display("End of simulation");
  $finish;
end

endmodule

dev/sram/sram_tb.vcd
$date
	Mon Jul  5 22:14:33 2021
$end
$version
	Icarus Verilog
$end
$timescale
	1ps
$end
$scope module sram_tb $end
$var wire 1 ! mix_read $end
$var wire 12 " mix_addr_out [11:0] $end
$var reg 1 # clk $end
$var reg 31 $ mix_data [30:0] $end
$var reg 1 % reset $end
$var reg 1 & startR $end
$var reg 1 ' startW $end
$scope module SRAM $end
$var wire 10 ( block [9:0] $end
$var wire 1 # clk $end
$var wire 1 ) last $end
$var wire 12 * mix_addr_in [11:0] $end
$var wire 31 + mix_data_in [30:0] $end
$var wire 1 % reset $end
$var wire 1 , sram_cen $end
$var wire 1 - sram_oen $end
$var wire 1 . sram_wen $end
$var wire 1 & startR $end
$var wire 1 ' startW $end
$var wire 1 / stop $end
$var wire 16 0 sram_data [15:0] $end
$var wire 16 1 dataW [15:0] $end
$var reg 2 2 count [1:0] $end
$var reg 16 3 datah [15:0] $end
$var reg 16 4 datan [15:0] $end
$var reg 12 5 mix_addr_out [11:0] $end
$var reg 31 6 mix_data_out [30:0] $end
$var reg 1 ! mix_read $end
$var reg 1 7 mix_write $end
$var reg 1 8 read $end
$var reg 18 9 sram_addr [17:0] $end
$var reg 1 : sram_ce $end
$var reg 1 ; sram_oe $end
$var reg 1 < sram_we $end
$var reg 1 = start2 $end
$var reg 1 > startR2 $end
$var reg 1 ? write $end
$upscope $end
$upscope $end
$enddefinitions $end
#0
$dumpvars
x?
x>
x=
x<
x;
x:
bx 9
x8
x7
bx 6
bx 5
bx 4
bx 3
bx 2
bx 1
bx 0
x/
x.
x-
x,
bx +
b0 *
x)
b1000101011 (
0'
0&
1%
bx $
0#
bx "
x!
$end
#50000
1.
1-
1,
bz 0
0=
0>
0!
07
0<
0;
0:
08
0?
b0 $
b0 +
1#
#100000
0#
#150000
1#
#200000
0#
#250000
1#
#300000
0%
0#
#350000
1#
#400000
1'
0#
#450000
b0 1
0/
0)
1=
b100010101100000000 9
b0 "
b0 5
1!
b0 2
1#
#500000
0'
0#
#550000
b110011100011 1
b110011100011 0
0,
b1001011001000110000110011100011 $
b1001011001000110000110011100011 +
1?
1:
b0 4
b0 3
0!
0=
1#
#600000
0#
#650000
0.
b100101100100011 3
b110011100011 4
b1 2
1<
b0 $
b0 +
1#
#700000
0#
#750000
b100101100100011 0
1.
b100101100100011 1
0<
b10 2
b100101100100011 4
b100010101100000001 9
1#
#800000
0#
#850000
0.
b1 "
b1 5
1!
b11 2
1<
1#
#900000
0#
#950000
b110011100011 0
1.
b110011100011 1
b1001011001000110000110011100011 $
b1001011001000110000110011100011 +
0<
b0 2
0!
b100010101100000010 9
1#
#1000000
0#
#1050000
0.
b110011100011 4
b1 2
1<
b0 $
b0 +
1#
#1100000
0#
#1150000
b100101100100011 0
1.
b100101100100011 1
0<
b10 2
b100101100100011 4
b100010101100000011 9
1#
#1200000
0#
#1250000
0.
b10 "
b10 5
1!
b11 2
1<
1#
#1300000
0#
#1350000
b110011100011 0
1.
b110011100011 1
b1001011001000110000110011100011 $
b1001011001000110000110011100011 +
0<
b0 2
0!
b100010101100000100 9
1#
#1400000
0#
#1450000
0.
b110011100011 4
b1 2
1<
b0 $
b0 +
1#
#1500000
0#
#1550000
b100101100100011 0
1.
b100101100100011 1
0<
b10 2
b100101100100011 4
b100010101100000101 9
1#
#1600000
0#
#1650000
0.
b11 "
b11 5
1!
b11 2
1<
1#
#1700000
0#
#1750000
b110011100011 0
1.
b110011100011 1
b1001011001000110000110011100011 $
b1001011001000110000110011100011 +
0<
b0 2
0!
b100010101100000110 9
1#
#1800000
0#
#1850000
0.
b110011100011 4
b1 2
1<
b0 $
b0 +
1#
#1900000
0#
#1950000
b100101100100011 0
1.
b100101100100011 1
0<
b10 2
b100101100100011 4
b100010101100000111 9
1#
#2000000
0#
#2050000
0.
b100 "
b100 5
1!
b11 2
1<
1#
#2100000
0#
#2150000
b110011100011 0
1.
b110011100011 1
b1001011001000110000110011100011 $
b1001011001000110000110011100011 +
0<
b0 2
0!
b100010101100001000 9
1#
#2200000
0#
#2250000
0.
b110011100011 4
b1 2
1<
b0 $
b0 +
1#
#2300000
0#
#2350000
b100101100100011 0
1.
b100101100100011 1
0<
b10 2
b100101100100011 4
b100010101100001001 9
1#
#2400000
0#
#2450000
0.
b101 "
b101 5
1!
b11 2
1<
1#
#2500000
0#
#2550000
b1101100100000011 0
1.
b1101100100000011 1
b1101100100000011 $
b1101100100000011 +
0<
b0 2
0!
b100010101100001010 9
1#
#2600000
0#
#2650000
0.
b0 3
b1101100100000011 4
b1 2
1<
b0 $
b0 +
1#
#2700000
0#
#2750000
b0 0
1.
b0 1
0<
b10 2
b0 4
b100010101100001011 9
1#
#2800000
0#
#2850000
0.
b110 "
b110 5
1!
b11 2
1<
1#
#2900000
0#
#2950000
b1101100100000011 0
b1101100100000011 1
1.
b1101100100000011 $
b1101100100000011 +
0<
b0 2
0!
b100010101100001100 9
1#
#3000000
0#
#3050000
0.
b1101100100000011 4
b1 2
1<
b0 $
b0 +
1#
#3100000
0#
#3150000
b0 0
1.
b0 1
0<
b10 2
b0 4
b100010101100001101 9
1#
#3200000
0#
#3250000
0.
b111 "
b111 5
1!
b11 2
1<
1#
#3300000
0#
#3350000
b1101100100000011 0
b1101100100000011 1
1.
b1101100100000011 $
b1101100100000011 +
0<
b0 2
0!
b100010101100001110 9
1#
#3400000
0#
#3450000
0.
b1101100100000011 4
b1 2
1<
b0 $
b0 +
1#
#3500000
0#
#3550000
b0 0
1.
b0 1
0<
b10 2
b0 4
b100010101100001111 9
1#
#3600000
0#
#3650000
0.
b1000 "
b1000 5
1!
b11 2
1<
1#
#3700000
0#
#3750000
b1101100100000011 0
b1101100100000011 1
1.
b1101100100000011 $
b1101100100000011 +
0<
b0 2
0!
b100010101100010000 9
1#
#3800000
0#
#3850000
0.
b1101100100000011 4
b1 2
1<
b0 $
b0 +
1#
#3900000
0#
#3950000
b0 0
1.
b0 1
0<
b10 2
b0 4
b100010101100010001 9
1#
#4000000
0#
#4050000
0.
b1001 "
b1001 5
1!
b11 2
1<
1#
#4100000
0#
#4150000
b1101100100000011 0
b1101100100000011 1
1.
b1101100100000011 $
b1101100100000011 +
0<
b0 2
0!
b100010101100010010 9
1#
#4200000
0#
#4250000
0.
b1101100100000011 4
b1 2
1<
b0 $
b0 +
1#
#4300000
0#
#4350000
b0 0
1.
b0 1
0<
b10 2
b0 4
b100010101100010011 9
1#
#4400000
0#
#4450000
0.
b1010 "
b1010 5
1!
b11 2
1<
1#
#4500000
0#
#4550000
b10001101010 0
b10001101010 1
1.
b10000010001101010 $
b10000010001101010 +
0<
b0 2
0!
b100010101100010100 9
1#
#4600000
0#
#4650000
0.
b1 3
b10001101010 4
b1 2
1<
b0 $
b0 +
1#
#4700000
0#
#4750000
b1 0
1.
b1 1
0<
b10 2
b1 4
b100010101100010101 9
1#
#4800000
0#
#4850000
0.
b1011 "
b1011 5
1!
b11 2
1<
1#
#4900000
0#
#4950000
bx 0
1.
bx 1
bx $
bx +
0<
b0 2
0!
b100010101100010110 9
1#
#5000000
0#
#5050000
0.
b0xxxxxxxxxxxxxxx 3
bx 4
b1 2
1<
b0 $
b0 +
1#
#5100000
0#
#5150000
b0xxxxxxxxxxxxxxx 0
1.
b0xxxxxxxxxxxxxxx 1
0<
b10 2
b0xxxxxxxxxxxxxxx 4
b100010101100010111 9
1#
#5200000
0#
#5250000
0.
b1100 "
b1100 5
1!
b11 2
1<
1#
#5300000
0#
#5350000
bx 0
1.
bx 1
bx $
bx +
0<
b0 2
0!
b100010101100011000 9
1#
#5400000
0#
#5450000
0.
bx 4
b1 2
1<
b0 $
b0 +
1#
#5500000
1&
0#
#5550000
b0 0
1.
b0 1
0<
b0 2
b0xxxxxxxxxxxxxxx 4
b0 "
b0 5
b100010101100000000 9
1>
1#
#5600000
0&
0#
#5650000
0.
0-
0>
b0 3
b0 4
b1 2
1<
1;
18
1#
#5700000
0#
#5750000
1.
0<
b10 2
b100010101100000001 9
1#
#5800000
0#
#5850000
0.
b1 "
b1 5
1!
17
b0xxxxxxxxxxxxxxxx 6
b11 2
1<
1#
#5900000
0#
#5950000
b110011100011 0
b110011100011 1
1.
b1001011001000110000110011100011 $
b1001011001000110000110011100011 +
0<
b0 2
07
0!
b10 "
b10 5
b100010101100000010 9
1#
#6000000
0#
#6050000
0.
b100101100100011 3
b110011100011 4
b110011100011 6
b1 2
1<
b0 $
b0 +
1#
#6100000
0#
#6150000
b100101100100011 0
1.
b100101100100011 1
0<
b10 2
b100101100100011 4
b100010101100000011 9
1#
#6200000
0#
#6250000
0.
b11 "
b11 5
1!
17
b1001011001000110000110011100011 6
b11 2
1<
1#
#6300000
0#
#6350000
b110011100011 0
1.
b110011100011 1
b1001011001000110000110011100011 $
b1001011001000110000110011100011 +
0<
b0 2
07
0!
b100 "
b100 5
b100010101100000100 9
1#
#6400000
0#
#6450000
0.
b110011100011 4
b110011100011 6
b1 2
1<
b0 $
b0 +
1#
#6500000
0#
#6550000
b100101100100011 0
1.
b100101100100011 1
0<
b10 2
b100101100100011 4
b100010101100000101 9
1#
#6600000
0#
#6650000
0.
b101 "
b101 5
1!
17
b1001011001000110000110011100011 6
b11 2
1<
1#
#6700000
0#
#6750000
b1101100100000011 0
1.
b1101100100000011 1
b1101100100000011 $
b1101100100000011 +
0<
b0 2
07
0!
b110 "
b110 5
b100010101100000110 9
1#
#6800000
0#
#6850000
0.
b0 3
b1101100100000011 4
b1101100100000011 6
b1 2
1<
b0 $
b0 +
1#
#6900000
0#
#6950000
b0 0
1.
b0 1
0<
b10 2
b0 4
b100010101100000111 9
1#
#7000000
0#
#7050000
0.
b111 "
b111 5
1!
17
b11 2
1<
1#
#7100000
0#
#7150000
b1101100100000011 0
b1101100100000011 1
1.
b1101100100000011 $
b1101100100000011 +
0<
b0 2
07
0!
b1000 "
b1000 5
b100010101100001000 9
1#
#7200000
0#
#7250000
0.
b1101100100000011 4
b1 2
1<
b0 $
b0 +
1#
#7300000
0#
#7350000
b0 0
1.
b0 1
0<
b10 2
b0 4
b100010101100001001 9
1#
#7400000
0#
#7450000
0.
b1001 "
b1001 5
1!
17
b11 2
1<
1#
#7500000
0#
#7550000
b1101100100000011 0
b1101100100000011 1
1.
b1101100100000011 $
b1101100100000011 +
0<
b0 2
07
0!
b1010 "
b1010 5
b100010101100001010 9
1#
#7600000
0#
#7650000
0.
b1101100100000011 4
b1 2
1<
b0 $
b0 +
1#
#7700000
0#
#7750000
b0 0
1.
b0 1
0<
b10 2
b0 4
b100010101100001011 9
1#
#7800000
0#
#7850000
0.
b1011 "
b1011 5
1!
17
b11 2
1<
1#
#7900000
0#
#7950000
bx 0
bx 1
1.
bx $
bx +
0<
b0 2
07
0!
b1100 "
b1100 5
b100010101100001100 9
1#
#8000000
0#
#8050000
0.
b0xxxxxxxxxxxxxxx 3
bx 4
b0xxxxxxxxxxxxxxxx 6
b1 2
1<
b0 $
b0 +
1#
#8100000
0#
#8150000
b0xxxxxxxxxxxxxxx 0
1.
b0xxxxxxxxxxxxxxx 1
0<
b10 2
b0xxxxxxxxxxxxxxx 4
b100010101100001101 9
1#
#8200000
0#
#8250000
0.
b1101 "
b1101 5
1!
17
bx 6
b11 2
1<
1#
#8300000
0#
#8350000
bx 0
1.
bx 1
bx $
bx +
0<
b0 2
07
0!
b1110 "
b1110 5
b100010101100001110 9
1#
#8400000
0#
#8450000
0.
bx 4
b0xxxxxxxxxxxxxxxx 6
b1 2
1<
b0 $
b0 +
1#
#8500000
0#
#8550000
b0xxxxxxxxxxxxxxx 0
1.
b0xxxxxxxxxxxxxxx 1
0<
b10 2
b0xxxxxxxxxxxxxxx 4
b100010101100001111 9
1#
#8600000
0#
#8650000
0.
b1111 "
b1111 5
1!
17
bx 6
b11 2
1<
1#
#8700000
0#
#8750000
bx 0
1.
bx 1
bx $
bx +
0<
b0 2
07
0!
b10000 "
b10000 5
b100010101100010000 9
1#
#8800000
0#
#8850000
0.
bx 4
b0xxxxxxxxxxxxxxxx 6
b1 2
1<
b0 $
b0 +
1#
#8900000
0#
#8950000
b0xxxxxxxxxxxxxxx 0
1.
b0xxxxxxxxxxxxxxx 1
0<
b10 2
b0xxxxxxxxxxxxxxx 4
b100010101100010001 9
1#
#9000000
0#
#9050000
0.
b10001 "
b10001 5
1!
17
bx 6
b11 2
1<
1#
#9100000
0#
#9150000
bx 0
1.
bx 1
bx $
bx +
0<
b0 2
07
0!
b10010 "
b10010 5
b100010101100010010 9
1#
#9200000
0#
#9250000
0.
bx 4
b0xxxxxxxxxxxxxxxx 6
b1 2
1<
b0 $
b0 +
1#
#9300000
0#
#9350000
b0xxxxxxxxxxxxxxx 0
1.
b0xxxxxxxxxxxxxxx 1
0<
b10 2
b0xxxxxxxxxxxxxxx 4
b100010101100010011 9
1#
#9400000
0#
#9450000
0.
b10011 "
b10011 5
1!
17
bx 6
b11 2
1<
1#
#9500000
0#
#9550000
bx 0
1.
bx 1
bx $
bx +
0<
b0 2
07
0!
b10100 "
b10100 5
b100010101100010100 9
1#
#9600000
0#
#9650000
0.
bx 4
b0xxxxxxxxxxxxxxxx 6
b1 2
1<
b0 $
b0 +
1#
#9700000
0#
#9750000
b0xxxxxxxxxxxxxxx 0
1.
b0xxxxxxxxxxxxxxx 1
0<
b10 2
b0xxxxxxxxxxxxxxx 4
b100010101100010101 9
1#
#9800000
0#
#9850000
0.
b10101 "
b10101 5
1!
17
bx 6
b11 2
1<
1#
#9900000
0#
#9950000
bx 0
1.
bx 1
bx $
bx +
0<
b0 2
07
0!
b10110 "
b10110 5
b100010101100010110 9
1#
#10000000
0#
#10050000
0.
bx 4
b0xxxxxxxxxxxxxxxx 6
b1 2
1<
b0 $
b0 +
1#
#10100000
0#
#10150000
b0xxxxxxxxxxxxxxx 0
1.
b0xxxxxxxxxxxxxxx 1
0<
b10 2
b0xxxxxxxxxxxxxxx 4
b100010101100010111 9
1#
#10200000
0#
#10250000
0.
b10111 "
b10111 5
1!
17
bx 6
b11 2
1<
1#
#10300000
0#
#10350000
bx 0
1.
bx 1
bx $
bx +
0<
b0 2
07
0!
b11000 "
b11000 5
b100010101100011000 9
1#
#10400000
0#
#10450000
0.
bx 4
b0xxxxxxxxxxxxxxxx 6
b1 2
1<
b0 $
b0 +
1#
#10500000
0#
#10550000
b0xxxxxxxxxxxxxxx 0
1.
b0xxxxxxxxxxxxxxx 1
0<
b10 2
b0xxxxxxxxxxxxxxx 4
b100010101100011001 9
1#
#10600000
0#
#10650000
0.
b11001 "
b11001 5
1!
17
bx 6
b11 2
1<
1#
#10700000
0#
#10750000
bx 0
1.
bx 1
bx $
bx +
0<
b0 2
07
0!
b11010 "
b11010 5
b100010101100011010 9
1#
#10800000
0#
#10850000
0.
bx 4
b0xxxxxxxxxxxxxxxx 6
b1 2
1<
b0 $
b0 +
1#
#10900000
0#
#10950000
b0xxxxxxxxxxxxxxx 0
1.
b0xxxxxxxxxxxxxxx 1
0<
b10 2
b0xxxxxxxxxxxxxxx 4
b100010101100011011 9
1#
#11000000
0#
#11050000
0.
b11011 "
b11011 5
1!
17
bx 6
b11 2
1<
1#
#11100000
0#
#11150000
bx 0
1.
bx 1
bx $
bx +
0<
b0 2
07
0!
b11100 "
b11100 5
b100010101100011100 9
1#
#11200000
0#
#11250000
0.
bx 4
b0xxxxxxxxxxxxxxxx 6
b1 2
1<
b0 $
b0 +
1#
#11300000
0#
#11350000
b0xxxxxxxxxxxxxxx 0
1.
b0xxxxxxxxxxxxxxx 1
0<
b10 2
b0xxxxxxxxxxxxxxx 4
b100010101100011101 9
1#
#11400000
0#
#11450000
0.
b11101 "
b11101 5
1!
17
bx 6
b11 2
1<
1#
#11500000
0#
#11550000
bx 0
1.
bx 1
bx $
bx +
0<
b0 2
07
0!
b11110 "
b11110 5
b100010101100011110 9
1#
#11600000
0#
#11650000
0.
bx 4
b0xxxxxxxxxxxxxxxx 6
b1 2
1<
b0 $
b0 +
1#
#11700000
0#
#11750000
b0xxxxxxxxxxxxxxx 0
1.
b0xxxxxxxxxxxxxxx 1
0<
b10 2
b0xxxxxxxxxxxxxxx 4
b100010101100011111 9
1#
#11800000
0#
#11850000
0.
b11111 "
b11111 5
1!
17
bx 6
b11 2
1<
1#
#11900000
0#
#11950000
bx 0
1.
bx 1
bx $
bx +
0<
b0 2
07
0!
b100000 "
b100000 5
b100010101100100000 9
1#
#12000000
0#
#12050000
0.
bx 4
b0xxxxxxxxxxxxxxxx 6
b1 2
1<
b0 $
b0 +
1#
#12100000
0#
#12150000
b0xxxxxxxxxxxxxxx 0
1.
b0xxxxxxxxxxxxxxx 1
0<
b10 2
b0xxxxxxxxxxxxxxx 4
b100010101100100001 9
1#
#12200000
0#
#12250000
0.
b100001 "
b100001 5
1!
17
bx 6
b11 2
1<
1#
#12300000
0#
#12350000
bx 0
1.
bx 1
bx $
bx +
0<
b0 2
07
0!
b100010 "
b100010 5
b100010101100100010 9
1#
#12400000
0#
#12450000
0.
bx 4
b0xxxxxxxxxxxxxxxx 6
b1 2
1<
b0 $
b0 +
1#
#12500000
0#
#12550000
b0xxxxxxxxxxxxxxx 0
1.
b0xxxxxxxxxxxxxxx 1
0<
b10 2
b0xxxxxxxxxxxxxxx 4
b100010101100100011 9
1#
#12600000
0#
#12650000
0.
b100011 "
b100011 5
1!
17
bx 6
b11 2
1<
1#
#12700000
0#
#12750000
bx 0
1.
bx 1
bx $
bx +
0<
b0 2
07
0!
b100100 "
b100100 5
b100010101100100100 9
1#
#12800000
0#
#12850000
0.
bx 4
b0xxxxxxxxxxxxxxxx 6
b1 2
1<
b0 $
b0 +
1#
#12900000
0#
#12950000
b0xxxxxxxxxxxxxxx 0
1.
b0xxxxxxxxxxxxxxx 1
0<
b10 2
b0xxxxxxxxxxxxxxx 4
b100010101100100101 9
1#
#13000000
0#
#13050000
0.
b100101 "
b100101 5
1!
17
bx 6
b11 2
1<
1#
#13100000
0#
#13150000
bx 0
1.
bx 1
bx $
bx +
0<
b0 2
07
0!
b100110 "
b100110 5
b100010101100100110 9
1#
#13200000
0#
#13250000
0.
bx 4
b0xxxxxxxxxxxxxxxx 6
b1 2
1<
b0 $
b0 +
1#
#13300000
0#
#13350000
b0xxxxxxxxxxxxxxx 0
1.
b0xxxxxxxxxxxxxxx 1
0<
b10 2
b0xxxxxxxxxxxxxxx 4
b100010101100100111 9
1#
#13400000
0#
#13450000
0.
b100111 "
b100111 5
1!
17
bx 6
b11 2
1<
1#
#13500000
0#
#13550000
bx 0
1.
bx 1
bx $
bx +
0<
b0 2
07
0!
b101000 "
b101000 5
b100010101100101000 9
1#
#13600000
0#
#13650000
0.
bx 4
b0xxxxxxxxxxxxxxxx 6
b1 2
1<
b0 $
b0 +
1#
#13700000
0#
#13750000
b0xxxxxxxxxxxxxxx 0
1.
b0xxxxxxxxxxxxxxx 1
0<
b10 2
b0xxxxxxxxxxxxxxx 4
b100010101100101001 9
1#
#13800000
0#
#13850000
0.
b101001 "
b101001 5
1!
17
bx 6
b11 2
1<
1#
#13900000
0#
#13950000
bx 0
1.
bx 1
bx $
bx +
0<
b0 2
07
0!
b101010 "
b101010 5
b100010101100101010 9
1#
#14000000
0#
#14050000
0.
bx 4
b0xxxxxxxxxxxxxxxx 6
b1 2
1<
b0 $
b0 +
1#
#14100000
0#
#14150000
b0xxxxxxxxxxxxxxx 0
1.
b0xxxxxxxxxxxxxxx 1
0<
b10 2
b0xxxxxxxxxxxxxxx 4
b100010101100101011 9
1#
#14200000
0#
#14250000
0.
b101011 "
b101011 5
1!
17
bx 6
b11 2
1<
1#
#14300000
0#
#14350000
bx 0
1.
bx 1
bx $
bx +
0<
b0 2
07
0!
b101100 "
b101100 5
b100010101100101100 9
1#
#14400000
0#
#14450000
0.
bx 4
b0xxxxxxxxxxxxxxxx 6
b1 2
1<
b0 $
b0 +
1#
#14500000
0#
#14550000
b0xxxxxxxxxxxxxxx 0
1.
b0xxxxxxxxxxxxxxx 1
0<
b10 2
b0xxxxxxxxxxxxxxx 4
b100010101100101101 9
1#
#14600000
0#
#14650000
0.
b101101 "
b101101 5
1!
17
bx 6
b11 2
1<
1#
#14700000
0#
#14750000
bx 0
1.
bx 1
bx $
bx +
0<
b0 2
07
0!
b101110 "
b101110 5
b100010101100101110 9
1#
#14800000
0#
#14850000
0.
bx 4
b0xxxxxxxxxxxxxxxx 6
b1 2
1<
b0 $
b0 +
1#
#14900000
0#
#14950000
b0xxxxxxxxxxxxxxx 0
1.
b0xxxxxxxxxxxxxxx 1
0<
b10 2
b0xxxxxxxxxxxxxxx 4
b100010101100101111 9
1#
#15000000
0#
#15050000
0.
b101111 "
b101111 5
1!
17
bx 6
b11 2
1<
1#
#15100000
0#
#15150000
bx 0
1.
bx 1
bx $
bx +
0<
b0 2
07
0!
b110000 "
b110000 5
b100010101100110000 9
1#
#15200000
0#
#15250000
0.
bx 4
b0xxxxxxxxxxxxxxxx 6
b1 2
1<
b0 $
b0 +
1#
#15300000
0#
#15350000
b0xxxxxxxxxxxxxxx 0
1.
b0xxxxxxxxxxxxxxx 1
0<
b10 2
b0xxxxxxxxxxxxxxx 4
b100010101100110001 9
1#
#15400000
0#
#15450000
0.
b110001 "
b110001 5
1!
17
bx 6
b11 2
1<
1#
#15500000
0#
#15550000
bx 0
1.
bx 1
bx $
bx +
0<
b0 2
07
0!
b110010 "
b110010 5
b100010101100110010 9
1#
#15600000
0#
#15650000
0.
bx 4
b0xxxxxxxxxxxxxxxx 6
b1 2
1<
b0 $
b0 +
1#
#15700000
0#
#15750000
b0xxxxxxxxxxxxxxx 0
1.
b0xxxxxxxxxxxxxxx 1
0<
b10 2
b0xxxxxxxxxxxxxxx 4
b100010101100110011 9
1#
#15800000
0#
#15850000
0.
b110011 "
b110011 5
1!
17
bx 6
b11 2
1<
1#
#15900000
0#
#15950000
bx 0
1.
bx 1
bx $
bx +
0<
b0 2
07
0!
b110100 "
b110100 5
b100010101100110100 9
1#
#16000000
0#
#16050000
0.
bx 4
b0xxxxxxxxxxxxxxxx 6
b1 2
1<
b0 $
b0 +
1#
#16100000
0#
#16150000
b0xxxxxxxxxxxxxxx 0
1.
b0xxxxxxxxxxxxxxx 1
0<
b10 2
b0xxxxxxxxxxxxxxx 4
b100010101100110101 9
1#
#16200000
0#
#16250000
0.
b110101 "
b110101 5
1!
17
bx 6
b11 2
1<
1#
#16300000
0#
#16350000
bx 0
1.
bx 1
bx $
bx +
0<
b0 2
07
0!
b110110 "
b110110 5
b100010101100110110 9
1#
#16400000
0#
#16450000
0.
bx 4
b0xxxxxxxxxxxxxxxx 6
b1 2
1<
b0 $
b0 +
1#
#16500000
0#
#16550000
b0xxxxxxxxxxxxxxx 0
1.
b0xxxxxxxxxxxxxxx 1
0<
b10 2
b0xxxxxxxxxxxxxxx 4
b100010101100110111 9
1#
#16600000
0#
#16650000
0.
b110111 "
b110111 5
1!
17
bx 6
b11 2
1<
1#
#16700000
0#
#16750000
bx 0
1.
bx 1
bx $
bx +
0<
b0 2
07
0!
b111000 "
b111000 5
b100010101100111000 9
1#
#16800000
0#
#16850000
0.
bx 4
b0xxxxxxxxxxxxxxxx 6
b1 2
1<
b0 $
b0 +
1#
#16900000
0#
#16950000
b0xxxxxxxxxxxxxxx 0
1.
b0xxxxxxxxxxxxxxx 1
0<
b10 2
b0xxxxxxxxxxxxxxx 4
b100010101100111001 9
1#
#17000000
0#
#17050000
0.
b111001 "
b111001 5
1!
17
bx 6
b11 2
1<
1#
#17100000
0#
#17150000
bx 0
1.
bx 1
bx $
bx +
0<
b0 2
07
0!
b111010 "
b111010 5
b100010101100111010 9
1#
#17200000
0#
#17250000
0.
bx 4
b0xxxxxxxxxxxxxxxx 6
b1 2
1<
b0 $
b0 +
1#
#17300000
0#
#17350000
b0xxxxxxxxxxxxxxx 0
1.
b0xxxxxxxxxxxxxxx 1
0<
b10 2
b0xxxxxxxxxxxxxxx 4
b100010101100111011 9
1#
#17400000
0#
#17450000
0.
b111011 "
b111011 5
1!
17
bx 6
b11 2
1<
1#
#17500000
0#
#17550000
bx 0
1.
bx 1
bx $
bx +
0<
b0 2
07
0!
b111100 "
b111100 5
b100010101100111100 9
1#
#17600000
0#
#17650000
0.
bx 4
b0xxxxxxxxxxxxxxxx 6
b1 2
1<
b0 $
b0 +
1#
#17700000
0#
#17750000
b0xxxxxxxxxxxxxxx 0
1.
b0xxxxxxxxxxxxxxx 1
0<
b10 2
b0xxxxxxxxxxxxxxx 4
b100010101100111101 9
1#
#17800000
0#
#17850000
0.
b111101 "
b111101 5
1!
17
bx 6
b11 2
1<
1#
#17900000
0#
#17950000
bx 0
1.
bx 1
bx $
bx +
0<
b0 2
07
0!
b111110 "
b111110 5
b100010101100111110 9
1#
#18000000
0#
#18050000
0.
bx 4
b0xxxxxxxxxxxxxxxx 6
b1 2
1<
b0 $
b0 +
1#
#18100000
0#
#18150000
b0xxxxxxxxxxxxxxx 0
1.
b0xxxxxxxxxxxxxxx 1
0<
b10 2
b0xxxxxxxxxxxxxxx 4
b100010101100111111 9
1#
#18200000
0#
#18250000
0.
b111111 "
b111111 5
1!
17
bx 6
b11 2
1<
1#
#18300000
0#
